obkreator/__init__.py
obkreator/_config.py
obkreator/argparser.py
obkreator/feros.py
obkreator/grond.py
obkreator/obheader.py
obkreator/obkreator.py
obkreator/query.py
obkreator/types.py
obkreator/utils.py
obkreator/wfi.py
obkreator-0.4.1.dist-info/LICENCE.txt
obkreator-0.4.1.dist-info/METADATA
obkreator-0.4.1.dist-info/WHEEL
obkreator-0.4.1.dist-info/entry_points.txt
obkreator-0.4.1.dist-info/top_level.txt
obkreator-0.4.1.dist-info/RECORD
