Metadata-Version: 2.1
Name: obkreator
Version: 0.4.1
Summary: Observing block creator for ESO/2.2m telescope
Author-email: Régis Lachaume <regis.lachaume@gmail.com>
Project-URL: Source, https://github.com/loqueelvientoajuarez/obkreator
Classifier: Programming Language :: Python :: 3
Classifier: Development Status :: 3 - Alpha
Classifier: Operating System :: OS Independent
Classifier: Intended Audience :: Science/Research
Classifier: Topic :: Scientific/Engineering :: Astronomy
Classifier: License :: Public Domain
Requires-Python: >=3.9
License-File: LICENCE.txt
Requires-Dist: astropy (>=4.0)
Requires-Dist: numpy (>=1.17)
Requires-Dist: scipy (>=1.5)
Requires-Dist: astroquery (>=0.4)
